datasette_multiline_links/__init__.py
datasette_multiline_links-0.1.dist-info/LICENSE
datasette_multiline_links-0.1.dist-info/METADATA
datasette_multiline_links-0.1.dist-info/WHEEL
datasette_multiline_links-0.1.dist-info/entry_points.txt
datasette_multiline_links-0.1.dist-info/top_level.txt
datasette_multiline_links-0.1.dist-info/RECORD
