Metadata-Version: 2.1
Name: datasette-multiline-links
Version: 0.1
Summary: Make multiple newline separated URLs clickable in Datasette
Home-page: https://github.com/simonw/datasette-multiline-links
Author: Simon Willison
License: Apache License, Version 2.0
Project-URL: Issues, https://github.com/simonw/datasette-multiline-links/issues
Project-URL: CI, https://github.com/simonw/datasette-multiline-links/actions
Project-URL: Changelog, https://github.com/simonw/datasette-multiline-links/releases
Classifier: Framework :: Datasette
Classifier: License :: OSI Approved :: Apache Software License
Requires-Python: >=3.7
License-File: LICENSE
Requires-Dist: datasette
Provides-Extra: test
Requires-Dist: pytest ; extra == 'test'
Requires-Dist: pytest-asyncio ; extra == 'test'
